{
  "scrapedAt": "2026-04-14T12:19:33.291Z",
  "scrapedDate": "Tuesday, April 14, 2026 at 12:19 PM UTC",
  "source": "PrizePicks API",
  "sport": "NBA",
  "day": "tomorrow",
  "team": "Philadelphia 76ers",
  "totalProps": 16,
  "props": [
    {
      "player": "Tyrese Maxey",
      "stat": "Points",
      "line": 29.5,
      "sport": "NBA",
      "startTime": "04/15/26 06:40 PM CST",
      "startTimeCST": "04/15/26 06:40 PM CST",
      "startDateCST": "2026-04-15",
      "startTimeIso": "2026-04-15T19:40:00.000-04:00",
      "oddsType": "standard",
      "Team": "Philadelphia 76ers",
      "teamCode": "PHI",
      "Opponent": "Orlando Magic",
      "opponentCode": "ORL",
      "rank": 1858,
      "gameId": "151803"
    },
    {
      "player": "Tyrese Maxey",
      "stat": "Points",
      "line": 29.5,
      "sport": "NBA",
      "startTime": "04/15/26 06:40 PM CST",
      "startTimeCST": "04/15/26 06:40 PM CST",
      "startDateCST": "2026-04-15",
      "startTimeIso": "2026-04-15T19:40:00.000-04:00",
      "oddsType": "standard",
      "Team": "Philadelphia 76ers",
      "teamCode": "PHI",
      "Opponent": "Orlando Magic",
      "opponentCode": "ORL",
      "rank": 1867,
      "gameId": "151803"
    },
    {
      "player": "Paul George",
      "stat": "Points",
      "line": 21.5,
      "sport": "NBA",
      "startTime": "04/15/26 06:40 PM CST",
      "startTimeCST": "04/15/26 06:40 PM CST",
      "startDateCST": "2026-04-15",
      "startTimeIso": "2026-04-15T19:40:00.000-04:00",
      "oddsType": "standard",
      "Team": "Philadelphia 76ers",
      "teamCode": "PHI",
      "Opponent": "Orlando Magic",
      "opponentCode": "ORL",
      "rank": 1933,
      "gameId": "151803"
    },
    {
      "player": "VJ Edgecombe",
      "stat": "Points",
      "line": 16.5,
      "sport": "NBA",
      "startTime": "04/15/26 06:40 PM CST",
      "startTimeCST": "04/15/26 06:40 PM CST",
      "startDateCST": "2026-04-15",
      "startTimeIso": "2026-04-15T19:40:00.000-04:00",
      "oddsType": "standard",
      "Team": "Philadelphia 76ers",
      "teamCode": "PHI",
      "Opponent": "Orlando Magic",
      "opponentCode": "ORL",
      "rank": 1996,
      "gameId": "151803"
    },
    {
      "player": "Kelly Oubre",
      "stat": "Points",
      "line": 13.5,
      "sport": "NBA",
      "startTime": "04/15/26 06:40 PM CST",
      "startTimeCST": "04/15/26 06:40 PM CST",
      "startDateCST": "2026-04-15",
      "startTimeIso": "2026-04-15T19:40:00.000-04:00",
      "oddsType": "standard",
      "Team": "Philadelphia 76ers",
      "teamCode": "PHI",
      "Opponent": "Orlando Magic",
      "opponentCode": "ORL",
      "rank": 2038,
      "gameId": "151803"
    },
    {
      "player": "Quentin Grimes",
      "stat": "Points",
      "line": 10.5,
      "sport": "NBA",
      "startTime": "04/15/26 06:40 PM CST",
      "startTimeCST": "04/15/26 06:40 PM CST",
      "startDateCST": "2026-04-15",
      "startTimeIso": "2026-04-15T19:40:00.000-04:00",
      "oddsType": "standard",
      "Team": "Philadelphia 76ers",
      "teamCode": "PHI",
      "Opponent": "Orlando Magic",
      "opponentCode": "ORL",
      "rank": 2085,
      "gameId": "151803"
    },
    {
      "player": "Andre Drummond",
      "stat": "Points",
      "line": 6.5,
      "sport": "NBA",
      "startTime": "04/15/26 06:40 PM CST",
      "startTimeCST": "04/15/26 06:40 PM CST",
      "startDateCST": "2026-04-15",
      "startTimeIso": "2026-04-15T19:40:00.000-04:00",
      "oddsType": "standard",
      "Team": "Philadelphia 76ers",
      "teamCode": "PHI",
      "Opponent": "Orlando Magic",
      "opponentCode": "ORL",
      "rank": 2184,
      "gameId": "151803"
    },
    {
      "player": "Paul George",
      "stat": "Rebounds",
      "line": 5.5,
      "sport": "NBA",
      "startTime": "04/15/26 06:40 PM CST",
      "startTimeCST": "04/15/26 06:40 PM CST",
      "startDateCST": "2026-04-15",
      "startTimeIso": "2026-04-15T19:40:00.000-04:00",
      "oddsType": "standard",
      "Team": "Philadelphia 76ers",
      "teamCode": "PHI",
      "Opponent": "Orlando Magic",
      "opponentCode": "ORL",
      "rank": 2190,
      "gameId": "151803"
    },
    {
      "player": "VJ Edgecombe",
      "stat": "Rebounds",
      "line": 5.5,
      "sport": "NBA",
      "startTime": "04/15/26 06:40 PM CST",
      "startTimeCST": "04/15/26 06:40 PM CST",
      "startDateCST": "2026-04-15",
      "startTimeIso": "2026-04-15T19:40:00.000-04:00",
      "oddsType": "standard",
      "Team": "Philadelphia 76ers",
      "teamCode": "PHI",
      "Opponent": "Orlando Magic",
      "opponentCode": "ORL",
      "rank": 2194,
      "gameId": "151803"
    },
    {
      "player": "VJ Edgecombe",
      "stat": "Assists",
      "line": 5,
      "sport": "NBA",
      "startTime": "04/15/26 06:40 PM CST",
      "startTimeCST": "04/15/26 06:40 PM CST",
      "startDateCST": "2026-04-15",
      "startTimeIso": "2026-04-15T19:40:00.000-04:00",
      "oddsType": "standard",
      "Team": "Philadelphia 76ers",
      "teamCode": "PHI",
      "Opponent": "Orlando Magic",
      "opponentCode": "ORL",
      "rank": 2209,
      "gameId": "151803"
    },
    {
      "player": "Tyrese Maxey",
      "stat": "Turnovers",
      "line": 2.5,
      "sport": "NBA",
      "startTime": "04/15/26 06:40 PM CST",
      "startTimeCST": "04/15/26 06:40 PM CST",
      "startDateCST": "2026-04-15",
      "startTimeIso": "2026-04-15T19:40:00.000-04:00",
      "oddsType": "standard",
      "Team": "Philadelphia 76ers",
      "teamCode": "PHI",
      "Opponent": "Orlando Magic",
      "opponentCode": "ORL",
      "rank": 2300,
      "gameId": "151803"
    },
    {
      "player": "Paul George",
      "stat": "Steals",
      "line": 1.5,
      "sport": "NBA",
      "startTime": "04/15/26 06:40 PM CST",
      "startTimeCST": "04/15/26 06:40 PM CST",
      "startDateCST": "2026-04-15",
      "startTimeIso": "2026-04-15T19:40:00.000-04:00",
      "oddsType": "standard",
      "Team": "Philadelphia 76ers",
      "teamCode": "PHI",
      "Opponent": "Orlando Magic",
      "opponentCode": "ORL",
      "rank": 2320,
      "gameId": "151803"
    },
    {
      "player": "Kelly Oubre",
      "stat": "Turnovers",
      "line": 1.5,
      "sport": "NBA",
      "startTime": "04/15/26 06:40 PM CST",
      "startTimeCST": "04/15/26 06:40 PM CST",
      "startDateCST": "2026-04-15",
      "startTimeIso": "2026-04-15T19:40:00.000-04:00",
      "oddsType": "standard",
      "Team": "Philadelphia 76ers",
      "teamCode": "PHI",
      "Opponent": "Orlando Magic",
      "opponentCode": "ORL",
      "rank": 2338,
      "gameId": "151803"
    },
    {
      "player": "Andre Drummond",
      "stat": "Assists",
      "line": 1.5,
      "sport": "NBA",
      "startTime": "04/15/26 06:40 PM CST",
      "startTimeCST": "04/15/26 06:40 PM CST",
      "startDateCST": "2026-04-15",
      "startTimeIso": "2026-04-15T19:40:00.000-04:00",
      "oddsType": "standard",
      "Team": "Philadelphia 76ers",
      "teamCode": "PHI",
      "Opponent": "Orlando Magic",
      "opponentCode": "ORL",
      "rank": 2355,
      "gameId": "151803"
    },
    {
      "player": "Adem Bona",
      "stat": "Steals",
      "line": 0.5,
      "sport": "NBA",
      "startTime": "04/15/26 06:40 PM CST",
      "startTimeCST": "04/15/26 06:40 PM CST",
      "startDateCST": "2026-04-15",
      "startTimeIso": "2026-04-15T19:40:00.000-04:00",
      "oddsType": "standard",
      "Team": "Philadelphia 76ers",
      "teamCode": "PHI",
      "Opponent": "Orlando Magic",
      "opponentCode": "ORL",
      "rank": 2383,
      "gameId": "151803"
    },
    {
      "player": "VJ Edgecombe",
      "stat": "Blocked Shots",
      "line": 0.5,
      "sport": "NBA",
      "startTime": "04/15/26 06:40 PM CST",
      "startTimeCST": "04/15/26 06:40 PM CST",
      "startDateCST": "2026-04-15",
      "startTimeIso": "2026-04-15T19:40:00.000-04:00",
      "oddsType": "standard",
      "Team": "Philadelphia 76ers",
      "teamCode": "PHI",
      "Opponent": "Orlando Magic",
      "opponentCode": "ORL",
      "rank": 2391,
      "gameId": "151803"
    }
  ]
}